mypy_test/__init__.py
mypy_test/__main__.py
mypy_test/_cli.py
mypy_test/_message.py
mypy_test/_mypy.py
mypy_test/_source.py
mypy_test/py.typed
mypy_test-0.1.4.dist-info/entry_points.txt
mypy_test-0.1.4.dist-info/LICENSE
mypy_test-0.1.4.dist-info/WHEEL
mypy_test-0.1.4.dist-info/METADATA
mypy_test-0.1.4.dist-info/RECORD
