Metadata-Version: 2.1
Name: mypy-test
Version: 0.1.4
Summary: Test mypy plugins, stubs, custom types.
Home-page: https://github.com/orsinium-labs/mypy-test
License: MIT
Keywords: mypy,testing,stubs,plugins,typing
Author: Gram
Author-email: gram@orsinium.dev
Requires-Python: >=3.6
Classifier: Development Status :: 5 - Production/Stable
Classifier: Intended Audience :: Developers
Classifier: License :: OSI Approved :: MIT License
Classifier: Programming Language :: Python
Classifier: Topic :: Software Development
Classifier: Topic :: Software Development :: Libraries :: Python Modules
Requires-Dist: mypy
Requires-Dist: lxml
Requires-Dist: pytest ; extra == "test"
Provides-Extra: test
